maprule/__init__.py
maprule/fields.py
maprule-1.1.0.dist-info/LICENSE
maprule-1.1.0.dist-info/METADATA
maprule-1.1.0.dist-info/WHEEL
maprule-1.1.0.dist-info/top_level.txt
maprule-1.1.0.dist-info/RECORD
