Metadata-Version: 2.1
Name: maprule
Version: 1.1.0
Summary: package for validating values
Home-page: https://github.com/rubbiekelvin/maprule
Author: Rubbie Kelvin
Author-email: dev.rubbie@gmail.com
License: UNKNOWN
Platform: UNKNOWN
Classifier: Programming Language :: Python :: 3
Classifier: License :: OSI Approved :: MIT License
Classifier: Operating System :: OS Independent
License-File: LICENSE
